clibf/__init__.py
clibf/__main__.py
clibf-1.0.4.dist-info/LICENSE
clibf-1.0.4.dist-info/METADATA
clibf-1.0.4.dist-info/WHEEL
clibf-1.0.4.dist-info/entry_points.txt
clibf-1.0.4.dist-info/top_level.txt
clibf-1.0.4.dist-info/RECORD
