Metadata-Version: 2.1
Name: clibf
Version: 1.0.4
Summary: CLI tool to execute Brainfuck code from files and strings
Home-page: https://github.com/donno2048/bf-interpreter
Author: Elisha Hollander
License: MIT
Platform: UNKNOWN
Classifier: Programming Language :: Python :: 3
License-File: LICENSE
Requires-Dist: questionary (>=1.10.0)
